MANIFEST.in
setup.cfg
PersianStemmer/__init__.py
PersianStemmer/persian_stemmer.py
PersianStemmer/stemming_rule.py
PersianStemmer/utils.py
PersianStemmer/verb_stem.py
PersianStemmer.egg-info/PKG-INFO
PersianStemmer.egg-info/SOURCES.txt
PersianStemmer.egg-info/dependency_links.txt
PersianStemmer.egg-info/requires.txt
PersianStemmer.egg-info/top_level.txt
PersianStemmer/data/Dictionary.ar
PersianStemmer/data/Dictionary.fa
PersianStemmer/data/Mokassar.fa
PersianStemmer/data/PECL_Patterns.fa
PersianStemmer/data/Patterns.fa
PersianStemmer/data/VerbList.fa