Metadata-Version: 1.1
Name: PersianStemmer
Version: 1.0.0
Summary: Persian Stemmer for Python
Home-page: https://github.com/htaghizadeh/PersianStemmer-Python
Author: Hossein Taghi-Zadeh
Author-email: h.t.azeri@gmail.com
License: Copyright (c) 2016, Hossein Taghi-Zadeh
